vk_url_scraper/__init__.py
vk_url_scraper/__main__.py
vk_url_scraper/py.typed
vk_url_scraper/scraper.py
vk_url_scraper/utils.py
vk_url_scraper/version.py
vk_url_scraper-0.3.30.dist-info/LICENSE
vk_url_scraper-0.3.30.dist-info/METADATA
vk_url_scraper-0.3.30.dist-info/WHEEL
vk_url_scraper-0.3.30.dist-info/entry_points.txt
vk_url_scraper-0.3.30.dist-info/top_level.txt
vk_url_scraper-0.3.30.dist-info/RECORD
